{ 
	"display": { 
		"icon": { 
			"item": "growthcraft_apples:apple_door_item"
		},
	"title": { 
		"translate": "advancement.craft.apple_item"
	},
	"description": {
		"translate": "advancement.craft.apple_item.desc",
		"italic": true
	},
	"frame": "task",
	"parent": "growthcraft_apples:advancement_craft_apple_planks"
	},
	"criteria": {
		"craft_apple_door": {
			"trigger": "minecraft:inventory_changed",
			"contitions":{
				"items": [
					{
						"item": "growthcraft_apples:apple_door"
					}
				]
			}
		},
		"craft_apple_fence": {
			"trigger": "minecraft:inventory_changed",
			"contitions":{
				"items": [
					{
						"item": "growthcraft_apples:apple_fence"
					}
				]
			}
		},
		"craft_apple_fence_gate": {
			"trigger": "minecraft:inventory_changed",
			"contitions":{
				"items": [
					{
						"item": "growthcraft_apples:apple_fence_gate"
					}
				]
			}
		},
		"craft_apple_stairs": {
			"trigger": "minecraft:inventory_changed",
			"contitions":{
				"items": [
					{
						"item": "growthcraft_apples:apple_stairs"
					}
				]
			}
		},
		"craft_apple_wooden_slab": {
			"trigger": "minecraft:inventory_changed",
			"contitions":{
				"items": [
					{
						"item": "growthcraft_apples:apple_wooden_slab"
					}
				]
			}
		}
	},
	"requirements":[
		[
			"craft_apple_door", 
			"craft_apple_fence", 
			"craft_apple_fence_gate", 
			"craft_apple_stairs", 
			"craft_apple_wooden_slab"
		]
	]
}
